Metadata-Version: 2.1
Name: mysq2
Version: 0.0.15
Summary: exam copy
Author: kaushal bhatol
Author-email: <kaushal@bhatol.com>
Keywords: mysq,mysq2
Classifier: Development Status :: 1 - Planning
Classifier: Intended Audience :: Developers
Classifier: Programming Language :: Python :: 3
Classifier: Operating System :: Unix
Classifier: Operating System :: MacOS :: MacOS X
Classifier: Operating System :: Microsoft :: Windows
